converter/__init__.py
converter/database_worker.py
converter/fields_converter.py
converter/fields_converter_oneway.py
converter/advanced_ddl/__init__.py
converter/advanced_ddl/advanced_ddl_creator.py
converter/advanced_ddl/keys_generator.py
converter/advanced_ddl/text_size_generator.py
converter/config/__init__.py
converter/config/config_converter.py
converter/pg_ch_converter/__init__.py
converter/pg_ch_converter/schemas_checker.py
converter/pg_ch_converter/table_generator.py
etl_helper_talenttech-1.7.1.dist-info/LICENSE.txt
etl_helper_talenttech-1.7.1.dist-info/METADATA
etl_helper_talenttech-1.7.1.dist-info/WHEEL
etl_helper_talenttech-1.7.1.dist-info/top_level.txt
etl_helper_talenttech-1.7.1.dist-info/RECORD
