Metadata-Version: 2.1
Name: etl-helper-talenttech
Version: 1.7.1
Summary: TopMind ETL helper
Home-page: https://github.com/severgroup-tt/topmind-commons/tree/master/py/etl-helper
Author: Dmitry Utiralov
Author-email: d.utiralov@talenttech.ru
License: MIT
Classifier: Programming Language :: Python :: 3
Classifier: License :: OSI Approved :: MIT License
Classifier: Operating System :: OS Independent
Requires-Python: >=3.6
License-File: LICENSE.txt
Requires-Dist: sqlalchemy ==1.4.42
Requires-Dist: python-dateutil
Requires-Dist: clickhouse-sqlalchemy
Requires-Dist: sqlalchemy-vertica-python
Requires-Dist: psycopg2-binary
Requires-Dist: requests
